regenmaschine/__init__.py
regenmaschine/client.py
regenmaschine/const.py
regenmaschine/controller.py
regenmaschine/endpoints/__init__.py
regenmaschine/endpoints/api.py
regenmaschine/endpoints/diagnostics.py
regenmaschine/endpoints/machine.py
regenmaschine/endpoints/parser.py
regenmaschine/endpoints/program.py
regenmaschine/endpoints/provision.py
regenmaschine/endpoints/restriction.py
regenmaschine/endpoints/stats.py
regenmaschine/endpoints/watering.py
regenmaschine/endpoints/zone.py
regenmaschine/errors.py
regenmaschine/py.typed
regenmaschine-2024.1.0.dist-info/LICENSE
regenmaschine-2024.1.0.dist-info/METADATA
regenmaschine-2024.1.0.dist-info/WHEEL
regenmaschine-2024.1.0.dist-info/RECORD
