Metadata-Version: 2.1
Name: regenmaschine
Version: 2024.1.0
Summary: A simple API for RainMachine sprinkler controllers
Home-page: https://github.com/bachya/regenmaschine
License: MIT
Author: Aaron Bach
Author-email: bachya1208@gmail.com
Requires-Python: >=3.10,<4.0
Classifier: License :: OSI Approved :: MIT License
Classifier: Programming Language :: Python
Classifier: Programming Language :: Python :: 3
Classifier: Programming Language :: Python :: 3.10
Classifier: Programming Language :: Python :: 3.11
Classifier: Programming Language :: Python :: 3.12
Classifier: Programming Language :: Python :: Implementation :: CPython
Classifier: Programming Language :: Python :: Implementation :: PyPy
Requires-Dist: aiohttp (>=3.8.0)
Requires-Dist: certifi (>=2023.07.22)
Requires-Dist: frozenlist (>=1.4.0,<2.0.0)
Requires-Dist: typing-extensions (>=4.3.0,<5.0.0)
Requires-Dist: yarl (>=1.9.2)
Project-URL: Bug Tracker, https://github.com/bachya/regenmaschine/issues
Project-URL: Changelog, https://github.com/bachya/regenmaschine/releases
Project-URL: Repository, https://github.com/bachya/regenmaschine
